decorative_secrets/__init__.py
decorative_secrets/__main__.py
decorative_secrets/_utilities.py
decorative_secrets/callback.py
decorative_secrets/databricks.py
decorative_secrets/defaults.py
decorative_secrets/environment.py
decorative_secrets/errors.py
decorative_secrets/onepassword.py
decorative_secrets/py.typed
decorative_secrets/subprocess.py
decorative_secrets/utilities.py
decorative_secrets-0.8.5.dist-info/METADATA
decorative_secrets-0.8.5.dist-info/WHEEL
decorative_secrets-0.8.5.dist-info/entry_points.txt
decorative_secrets-0.8.5.dist-info/RECORD
