Metadata-Version: 2.4
Name: decorative-secrets
Version: 0.8.5
Summary: Decorators for Multi-Source Secret Retrieval
Project-URL: Documentation, https://decorative-secrets.enorganic.org
Project-URL: Repository, https://github.com/enorganic/decorative-secrets
Author-email: david@belais.me
License-Expression: MIT
Keywords: decorators,secrets
Requires-Python: ~=3.10
Requires-Dist: async-lru~=2.0
Requires-Dist: nest-asyncio~=1.6
Provides-Extra: all
Requires-Dist: azure-keyvault-secrets~=4.10; extra == 'all'
Requires-Dist: boto3~=1.42; extra == 'all'
Requires-Dist: databricks-sdk~=0.76; extra == 'all'
Requires-Dist: google-cloud-secret-manager~=2.26; extra == 'all'
Requires-Dist: onepassword-sdk~=0.3; extra == 'all'
Requires-Dist: onepasswordconnectsdk~=2.0; extra == 'all'
Provides-Extra: aws
Requires-Dist: boto3~=1.42; extra == 'aws'
Provides-Extra: azure
Requires-Dist: azure-keyvault-secrets~=4.10; extra == 'azure'
Provides-Extra: databricks
Requires-Dist: databricks-sdk; extra == 'databricks'
Provides-Extra: google
Requires-Dist: google-cloud-secret-manager~=2.26; extra == 'google'
Provides-Extra: onepassword
Requires-Dist: onepassword-sdk~=0.3; extra == 'onepassword'
Requires-Dist: onepasswordconnectsdk~=2.0; extra == 'onepassword'
